{
  "tabPane": [
    {
      "title": "SmartDashboard",
      "autoPopulate": true,
      "autoPopulatePrefix": "SmartDashboard/",
      "widgetPane": {
        "gridSize": 128.0,
        "showGrid": true,
        "hgap": 16.0,
        "vgap": 16.0,
        "tiles": {
          "4,3": {
            "size": [
              1,
              1
            ],
            "content": {
              "_type": "Text View",
              "_source0": "network_table:///SmartDashboard/BL pivot encoder",
              "_title": "BL pivot encoder"
            }
          },
          "4,2": {
            "size": [
              1,
              1
            ],
            "content": {
              "_type": "Text View",
              "_source0": "network_table:///SmartDashboard/FL pivot encoder",
              "_title": "FL pivot encoder"
            }
          },
          "5,3": {
            "size": [
              2,
              1
            ],
            "content": {
              "_type": "Text View",
              "_source0": "network_table:///SmartDashboard/BR pivot encoder",
              "_title": "BR pivot encoder"
            }
          },
          "5,2": {
            "size": [
              1,
              1
            ],
            "content": {
              "_type": "Text View",
              "_source0": "network_table:///SmartDashboard/FR pivot encoder",
              "_title": "FR pivot encoder"
            }
          },
          "2,2": {
            "size": [
              1,
              1
            ],
            "content": {
              "_type": "Text View",
              "_source0": "network_table:///SmartDashboard/FL goal theta",
              "_title": "FL goal theta"
            }
          },
          "2,3": {
            "size": [
              1,
              1
            ],
            "content": {
              "_type": "Text View",
              "_source0": "network_table:///SmartDashboard/BL goal theta",
              "_title": "BL goal theta"
            }
          },
          "4,1": {
            "size": [
              2,
              1
            ],
            "content": {
              "_type": "Text View",
              "_source0": "network_table:///SmartDashboard/BL pivot encoder (initial)",
              "_title": "BL pivot encoder (initial)"
            }
          },
          "4,0": {
            "size": [
              2,
              1
            ],
            "content": {
              "_type": "Text View",
              "_source0": "network_table:///SmartDashboard/FL pivot encoder (initial)",
              "_title": "FL pivot encoder (initial)"
            }
          },
          "6,1": {
            "size": [
              2,
              1
            ],
            "content": {
              "_type": "Text View",
              "_source0": "network_table:///SmartDashboard/BR pivot encoder (initial)",
              "_title": "BR pivot encoder (initial)"
            }
          },
          "6,0": {
            "size": [
              2,
              1
            ],
            "content": {
              "_type": "Text View",
              "_source0": "network_table:///SmartDashboard/FR pivot encoder (initial)",
              "_title": "FR pivot encoder (initial)"
            }
          },
          "3,3": {
            "size": [
              1,
              1
            ],
            "content": {
              "_type": "Text View",
              "_source0": "network_table:///SmartDashboard/BR goal theta",
              "_title": "BR goal theta"
            }
          },
          "3,2": {
            "size": [
              1,
              1
            ],
            "content": {
              "_type": "Text View",
              "_source0": "network_table:///SmartDashboard/FR goal theta",
              "_title": "FR goal theta"
            }
          },
          "8,0": {
            "size": [
              1,
              1
            ],
            "content": {
              "_type": "Text View",
              "_source0": "network_table:///SmartDashboard/Set Rotations",
              "_title": "Set Rotations"
            }
          },
          "9,0": {
            "size": [
              1,
              1
            ],
            "content": {
              "_type": "Text View",
              "_source0": "network_table:///SmartDashboard/Atan2 theta",
              "_title": "Atan2 theta"
            }
          },
          "10,0": {
            "size": [
              1,
              1
            ],
            "content": {
              "_type": "Text View",
              "_source0": "network_table:///SmartDashboard/joystick angle",
              "_title": "joystick angle"
            }
          }
        }
      }
    },
    {
      "title": "LiveWindow",
      "autoPopulate": true,
      "autoPopulatePrefix": "LiveWindow/",
      "widgetPane": {
        "gridSize": 128.0,
        "showGrid": true,
        "hgap": 16.0,
        "vgap": 16.0,
        "tiles": {
          "0,0": {
            "size": [
              2,
              4
            ],
            "content": {
              "_type": "Subsystem Layout",
              "_source0": "network_table:///LiveWindow/ExampleSubsystem",
              "_title": "ExampleSubsystem",
              "Layout/Label position": "BOTTOM",
              "_children": []
            }
          },
          "2,0": {
            "size": [
              2,
              4
            ],
            "content": {
              "_type": "Subsystem Layout",
              "_source0": "network_table:///LiveWindow/Ungrouped",
              "_title": "Ungrouped",
              "Layout/Label position": "BOTTOM",
              "_children": [
                {
                  "_type": "Speed Controller",
                  "_source0": "network_table:///LiveWindow/Ungrouped/PWMSparkMax[2]",
                  "_title": "PWMSparkMax[2]",
                  "Visuals/Orientation": "HORIZONTAL"
                },
                {
                  "_type": "Speed Controller",
                  "_source0": "network_table:///LiveWindow/Ungrouped/PWMSparkMax[4]",
                  "_title": "PWMSparkMax[4]",
                  "Visuals/Orientation": "HORIZONTAL"
                },
                {
                  "_type": "Speed Controller",
                  "_source0": "network_table:///LiveWindow/Ungrouped/PWMSparkMax[0]",
                  "_title": "PWMSparkMax[0]",
                  "Visuals/Orientation": "HORIZONTAL"
                },
                {
                  "_type": "Speed Controller",
                  "_source0": "network_table:///LiveWindow/Ungrouped/PWMSparkMax[1]",
                  "_title": "PWMSparkMax[1]",
                  "Visuals/Orientation": "HORIZONTAL"
                },
                {
                  "_type": "Speed Controller",
                  "_source0": "network_table:///LiveWindow/Ungrouped/PWMSparkMax[3]",
                  "_title": "PWMSparkMax[3]",
                  "Visuals/Orientation": "HORIZONTAL"
                },
                {
                  "_type": "Speed Controller",
                  "_source0": "network_table:///LiveWindow/Ungrouped/PWMSparkMax[9]",
                  "_title": "PWMSparkMax[9]",
                  "Visuals/Orientation": "HORIZONTAL"
                },
                {
                  "_type": "Speed Controller",
                  "_source0": "network_table:///LiveWindow/Ungrouped/PWMSparkMax[8]",
                  "_title": "PWMSparkMax[8]",
                  "Visuals/Orientation": "HORIZONTAL"
                },
                {
                  "_type": "Speed Controller",
                  "_source0": "network_table:///LiveWindow/Ungrouped/PWMSparkMax[12]",
                  "_title": "PWMSparkMax[12]",
                  "Visuals/Orientation": "HORIZONTAL"
                },
                {
                  "_type": "Speed Controller",
                  "_source0": "network_table:///LiveWindow/Ungrouped/PWMSparkMax[11]",
                  "_title": "PWMSparkMax[11]",
                  "Visuals/Orientation": "HORIZONTAL"
                },
                {
                  "_type": "Speed Controller",
                  "_source0": "network_table:///LiveWindow/Ungrouped/Spark[1]",
                  "_title": "Spark[1]",
                  "Visuals/Orientation": "HORIZONTAL"
                },
                {
                  "_type": "Speed Controller",
                  "_source0": "network_table:///LiveWindow/Ungrouped/Spark[0]",
                  "_title": "Spark[0]",
                  "Visuals/Orientation": "HORIZONTAL"
                },
                {
                  "_type": "Speed Controller",
                  "_source0": "network_table:///LiveWindow/Ungrouped/Spark[11]",
                  "_title": "Spark[11]",
                  "Visuals/Orientation": "HORIZONTAL"
                }
              ]
            }
          },
          "4,0": {
            "size": [
              2,
              4
            ],
            "content": {
              "_type": "Subsystem Layout",
              "_source0": "network_table:///LiveWindow/WheelDriveSubsystem",
              "_title": "WheelDriveSubsystem",
              "Layout/Label position": "BOTTOM",
              "_children": []
            }
          },
          "6,0": {
            "size": [
              2,
              4
            ],
            "content": {
              "_type": "Subsystem Layout",
              "_source0": "network_table:///LiveWindow/InputSubsystem",
              "_title": "InputSubsystem",
              "Layout/Label position": "BOTTOM",
              "_children": []
            }
          },
          "8,0": {
            "size": [
              2,
              4
            ],
            "content": {
              "_type": "Subsystem Layout",
              "_source0": "network_table:///LiveWindow/Shooter",
              "_title": "Shooter",
              "Layout/Label position": "BOTTOM",
              "_children": [
                {
                  "_type": "Subsystem Layout",
                  "_source0": "network_table:///LiveWindow/ShooterSubsystem",
                  "_title": "LiveWindow/ShooterSubsystem",
                  "Layout/Label position": "BOTTOM",
                  "_children": []
                }
              ]
            }
          }
        }
      }
    }
  ],
  "windowGeometry": {
    "x": -7.0,
    "y": 2.0,
    "width": 1612.0,
    "height": 865.0
  }
}